mullerpy/__init__.py
mullerpy/muller.py
mullerpy/py.typed
mullerpy-0.1.1.dist-info/METADATA
mullerpy-0.1.1.dist-info/WHEEL
mullerpy-0.1.1.dist-info/licenses/LICENSE.md
mullerpy-0.1.1.dist-info/RECORD
