Metadata-Version: 2.4
Name: mullerpy
Version: 0.1.1
Summary: A Python implementation of Muller's method.
Project-URL: source, https://github.com/fgittins/mullerpy
Author-email: Fabian Gittins <f.w.r.gittins@uu.nl>
License: MIT License
License-File: LICENSE.md
Classifier: Intended Audience :: Science/Research
Classifier: License :: OSI Approved :: MIT License
Classifier: Programming Language :: Python :: 3
Classifier: Programming Language :: Python :: 3.8
Classifier: Programming Language :: Python :: 3.9
Classifier: Programming Language :: Python :: 3.10
Classifier: Programming Language :: Python :: 3.11
Classifier: Programming Language :: Python :: 3.12
Classifier: Programming Language :: Python :: 3.13
Classifier: Topic :: Scientific/Engineering :: Mathematics
Requires-Python: >=3.8
